{
  "experiment_name": "sehri_et_al_inspired_setup",
  "feature_extraction": "WaveletFeatures",
  "classifier": "RandomForestClassifier",
  "augmentation": true,
  "start_time": "2026-05-01_14-31-01",
  "scores": {
    "fold_0_0": {
      "load_data_time": 4.060679451,
      "training_time": 13.312103372,
      "prediction_time": 1.097374851,
      "accuracy_score": 0.2575666466225697,
      "f1_macro": 0.14810057699895854,
      "confusion_matrix": "[[  46    6 1614]\n [   0    0 1660]\n [ 424    0 1239]]"
    },
    "fold_0_1": {
      "load_data_time": 4.499167222,
      "training_time": 11.053295176,
      "prediction_time": 1.161578751,
      "accuracy_score": 0.3674162070428511,
      "f1_macro": 0.21730005217909,
      "confusion_matrix": "[[1639    4   24]\n [1257   87   39]\n [1657    1    6]]"
    },
    "fold_0_2": {
      "load_data_time": 4.499167222,
      "training_time": 11.053295176,
      "prediction_time": 1.161578751,
      "accuracy_score": 0.5104,
      "f1_macro": 0.4970352607096345,
      "confusion_matrix": "[[ 474 1156   33]\n [ 193 1345  129]\n [ 539  398  733]]"
    }
  },
  "end_time": "2026-05-01_14-31-58"
}