{
  "experiment_name": "sehri_et_al_inspired_setup",
  "feature_extraction": "WaveletFeatures",
  "classifier": "RandomForestClassifier",
  "augmentation": true,
  "start_time": "2026-05-01_00-27-49",
  "scores": {
    "fold_0_0": {
      "load_data_time": 4.066338508,
      "training_time": 13.346805488,
      "prediction_time": 1.100722224,
      "accuracy_score": 0.269993986770896,
      "f1_macro": 0.15973315757651552,
      "confusion_matrix": "[[  71    5 1590]\n [   0    0 1660]\n [ 387    0 1276]]"
    },
    "fold_0_1": {
      "load_data_time": 4.483683879,
      "training_time": 11.005744918,
      "prediction_time": 1.16201821,
      "accuracy_score": 0.3657191344929996,
      "f1_macro": 0.21542570291358995,
      "confusion_matrix": "[[1634    7   26]\n [1262   85   36]\n [1657    2    5]]"
    },
    "fold_0_2": {
      "load_data_time": 4.483683879,
      "training_time": 11.005744918,
      "prediction_time": 1.16201821,
      "accuracy_score": 0.5038,
      "f1_macro": 0.49189689632193884,
      "confusion_matrix": "[[ 486 1146   31]\n [ 209 1311  147]\n [ 528  420  722]]"
    }
  },
  "end_time": "2026-05-01_00-28-46"
}